depgeist/__init__.py
depgeist/checker.py
depgeist/cli.py
depgeist/scanner.py
depgeist/updater.py
depgeist/utils.py
depgeist-1.0.0.dist-info/LICENSE
depgeist-1.0.0.dist-info/METADATA
depgeist-1.0.0.dist-info/WHEEL
depgeist-1.0.0.dist-info/entry_points.txt
depgeist-1.0.0.dist-info/top_level.txt
depgeist-1.0.0.dist-info/RECORD
