Metadata-Version: 2.2
Name: depgeist
Version: 1.0.0
Summary: A smart dependency checker for Python projects.
Home-page: https://github.com/yourname/DepGeist
Author: Your Name
Classifier: Programming Language :: Python :: 3
Classifier: License :: OSI Approved :: MIT License
Classifier: Operating System :: OS Independent
Requires-Python: >=3.6
License-File: LICENSE
Dynamic: author
Dynamic: classifier
Dynamic: description
Dynamic: description-content-type
Dynamic: home-page
Dynamic: requires-python
Dynamic: summary
